smartis_sdk_mg/__init__.py
smartis_sdk_mg/client.py
smartis_sdk_mg/common.py
smartis_sdk_mg/entity.py
smartis_sdk_mg/errors.py
smartis_sdk_mg/utils.py
smartis_sdk_mg-0.7.4.dist-info/LICENSE
smartis_sdk_mg-0.7.4.dist-info/METADATA
smartis_sdk_mg-0.7.4.dist-info/WHEEL
smartis_sdk_mg-0.7.4.dist-info/RECORD
