Metadata-Version: 2.1
Name: smartis-sdk-mg
Version: 0.7.4
Summary: SDK для Smartis API
License: MIT
Author: viktor
Author-email: vi.dave@yandex.ru
Requires-Python: >=3.10,<4.0
Classifier: License :: OSI Approved :: MIT License
Classifier: Programming Language :: Python :: 3
Classifier: Programming Language :: Python :: 3.10
Classifier: Programming Language :: Python :: 3.11
Requires-Dist: pandas (>=2,<3)
Requires-Dist: pydantic (>=2.0a1)
Requires-Dist: requests (>=2,<3)
